exonware/xwentity/base.py
exonware/xwentity/config.py
exonware/xwentity/contracts.py
exonware/xwentity/defs.py
exonware/xwentity/errors.py
exonware/xwentity/facade.py
exonware/xwentity/version.py
exonware_xwentity-0.0.1.2.dist-info/METADATA
exonware_xwentity-0.0.1.2.dist-info/WHEEL
exonware_xwentity-0.0.1.2.dist-info/licenses/LICENSE
exonware_xwentity-0.0.1.2.dist-info/RECORD
