Metadata-Version: 2.4
Name: exonware-xwentity
Version: 0.0.1.2
Summary: Entity management and relationship modeling library
Project-URL: Homepage, https://exonware.com
Project-URL: Repository, https://github.com/exonware/xentity
Project-URL: Documentation, https://github.com/exonware/xentity#readme
Author-email: "Eng. Muhammad AlShehri" <connect@exonware.com>
License: MIT
License-File: LICENSE
Keywords: entity,exonware,management,modeling,orm,relationship
Classifier: Development Status :: 3 - Alpha
Classifier: Intended Audience :: Developers
Classifier: License :: OSI Approved :: MIT License
Classifier: Operating System :: OS Independent
Classifier: Programming Language :: Python :: 3
Classifier: Programming Language :: Python :: 3.12
Classifier: Topic :: Software Development :: Libraries :: Python Modules
Requires-Python: >=3.12
Requires-Dist: exonware-xwsystem
Provides-Extra: dev
Requires-Dist: black>=23.0.0; extra == 'dev'
Requires-Dist: isort>=5.12.0; extra == 'dev'
Requires-Dist: mypy>=1.0.0; extra == 'dev'
Requires-Dist: pytest-asyncio>=0.21.0; extra == 'dev'
Requires-Dist: pytest-cov>=4.0.0; extra == 'dev'
Requires-Dist: pytest>=7.0.0; extra == 'dev'
Provides-Extra: full
Requires-Dist: exonware-xwaction>=0.0.1; extra == 'full'
Requires-Dist: exonware-xwdata>=0.0.1; extra == 'full'
Requires-Dist: exonware-xwnode>=0.0.1; extra == 'full'
Requires-Dist: exonware-xwschema>=0.0.1; extra == 'full'
Requires-Dist: exonware-xwsystem[full]; extra == 'full'
Provides-Extra: lazy
Requires-Dist: exonware-xwaction>=0.0.1; extra == 'lazy'
Requires-Dist: exonware-xwdata>=0.0.1; extra == 'lazy'
Requires-Dist: exonware-xwnode>=0.0.1; extra == 'lazy'
Requires-Dist: exonware-xwschema>=0.0.1; extra == 'lazy'
Requires-Dist: exonware-xwsystem[lazy]; extra == 'lazy'
